odesli/Odesli.py
odesli/__init__.py
odesli/entity/Entity.py
odesli/entity/EntityResult.py
odesli/entity/__init__.py
odesli/entity/album/Album.py
odesli/entity/album/AlbumResult.py
odesli/entity/album/__init__.py
odesli/entity/song/Song.py
odesli/entity/song/SongResult.py
odesli/entity/song/__init__.py
odesli-0.0.2.dist-info/LICENSE
odesli-0.0.2.dist-info/METADATA
odesli-0.0.2.dist-info/WHEEL
odesli-0.0.2.dist-info/top_level.txt
odesli-0.0.2.dist-info/RECORD
