Metadata-Version: 2.1
Name: odesli
Version: 0.0.2
Summary: Odesli API Python wrapper
Home-page: https://github.com/fabian-thomas/python-odesli
Author: Fabian Thomas
Author-email: fabian@fabianthomas.de
License: UNKNOWN
Project-URL: Bug Tracker, https://github.com/fabian-thomas/python-odesli/issues
Platform: UNKNOWN
Classifier: Programming Language :: Python :: 3
Classifier: License :: OSI Approved :: MIT License
Classifier: Operating System :: OS Independent
Requires-Python: >=3.6
License-File: LICENSE
Requires-Dist: requests
